Covid19ApiWrapper/__init__.py
Covid19ApiWrapper-0.0.4.dist-info/LICENSE
Covid19ApiWrapper-0.0.4.dist-info/METADATA
Covid19ApiWrapper-0.0.4.dist-info/WHEEL
Covid19ApiWrapper-0.0.4.dist-info/top_level.txt
Covid19ApiWrapper-0.0.4.dist-info/RECORD
