Metadata-Version: 2.1
Name: Covid19ApiWrapper
Version: 0.0.4
Summary: A basic API wrapper to interact with https://corona.lmao.ninja/.
Home-page: https://github.com/aerobotpro/covid-19-data-utils/tree/master/src/py/covid-19-utils
Author: Aero
Author-email: support@host-info.net
License: UNKNOWN
Platform: UNKNOWN
Classifier: Programming Language :: Python :: 3
Classifier: License :: OSI Approved :: MIT License
Classifier: Operating System :: OS Independent
Requires-Python: >=3.6
